{"data":{"allMarkdownRemark":{"edges":[{"node":{"id":"f5a7ed49-1a90-53ac-8fb0-a37f94f46236","frontmatter":{"id":"20180907a","url":"/2018/09/07/google-chrome-69-url-hidden-www-security-issue/","title":"Google Chrome 69 地址欄隱藏子域名後暴露的安全問題","date":"2018-09-07T03:48:03.125Z","tags":["GoogleChrome","地址欄","安全","Mac"],"headerImage":null,"description":"定期更新軟件可以修復其自身的漏洞，即使是 Google Chrome，它的更新也是有安全問題的。在 Chrome 69 的版本裡面，`www` 被認定為 `trivial` 的子域名，因而隱藏了它之前的字眼。雖然可以提升一點用戶體驗，但卻帶來了另外一個風險點。。。"}}}]}},"pageContext":{"isCreatedByStatefulCreatePages":false,"tag":"安全"}}