{"data":{"content":{"edges":[{"node":{"id":"e485d2e3-7004-53c0-b0d0-80f6fa66a2c8","html":"<p>經過一天的努力，我們成功進入最後 5 強。這次比賽都幾好玩，基本上由第一天中午吃到晚上，然後第二天回來也是吃吃吃。雖然最後沒有取得獎金，但也是學到很多的知識。比如說如何解決安裝 npm package 問題，更新 npm package 問題。</p>\n<p>第一天中午的時候已經把 Demo 做出來了，但是不知道為什麼刪除<code class=\"language-text\">node_modules</code>之後，Expo 就直接崩潰了。這是因為<code class=\"language-text\">package.json</code>裡面根本就沒有把完整的<code class=\"language-text\">dependencies</code>寫出來，當我輸入<code class=\"language-text\">npm install</code>的時候就不能順利安裝。於是我只能在 CodePen 裡面開一個<a href=\"http://codepen.io/calpa/pen/LyZjPm\" target=\"_blank\" rel=\"nofollow noopener noreferrer\">Pen</a>用來做控制器。</p>\n<h2 id=\"技術細節\"><a href=\"#%E6%8A%80%E8%A1%93%E7%B4%B0%E7%AF%80\" aria-label=\"技術細節 permalink\" class=\"anchor\"><svg aria-hidden=\"true\" focusable=\"false\" height=\"16\" version=\"1.1\" viewBox=\"0 0 16 16\" width=\"16\"><path fill-rule=\"evenodd\" d=\"M4 9h1v1H4c-1.5 0-3-1.69-3-3.5S2.55 3 4 3h4c1.45 0 3 1.69 3 3.5 0 1.41-.91 2.72-2 3.25V8.59c.58-.45 1-1.27 1-2.09C10 5.22 8.98 4 8 4H4c-.98 0-2 1.22-2 2.5S3 9 4 9zm9-3h-1v1h1c1 0 2 1.22 2 2.5S13.98 12 13 12H9c-.98 0-2-1.22-2-2.5 0-.83.42-1.64 1-2.09V6.25c-1.09.53-2 1.84-2 3.25C6 11.31 7.55 13 9 13h4c1.45 0 3-1.69 3-3.5S14.5 6 13 6z\"></path></svg></a>技術細節</h2>\n<p>這個控制器利用<code class=\"language-text\">window.addEventListener(&#39;deviceorientation&#39;, handleOrientation);</code>來監聽 Android 裝置的方向。當加速規偵測到裝置方向的變化，它就會調用<code class=\"language-text\">handleOrientation</code>方法。</p>\n<p>而<code class=\"language-text\">handleOrientation</code>方法有兩個目的：</p>\n<ol>\n<li>獲取<code class=\"language-text\">event</code>裡面的<code class=\"language-text\">alpha</code>, <code class=\"language-text\">beta</code>, <code class=\"language-text\">gamma</code>數值，它們分別代表裝置的 z 軸， x 軸， y 軸動向。</li>\n</ol>\n<p>z 軸介乎於 0 ~ 360 度之間，x 軸介乎於 -180 ~ 180 度之間，代表裝置的前後動向。y 軸介乎於 -90 ~ 90 度之間，代表裝置的左右動向。</p>\n<ol>\n<li>發送 event 到服務器。</li>\n</ol>\n<p>這個很簡單，利用 socket.io 就可以了。比如說<code class=\"language-text\">socket.emit(&#39;event&#39;);</code></p>\n<p>而在展示用戶數據的時候，我們用<a href=\"http://c3js.org/\" target=\"_blank\" rel=\"nofollow noopener noreferrer\">C3.js</a>來做實時渲染數據。利用 C3.js，我們很容易就可以產生 D3 圖表，而不是重寫 D3 代碼。我們也可以修改每一個元素的樣式。感覺再寫下去就變教學文了。。。</p>\n<h2 id=\"比賽照片\"><a href=\"#%E6%AF%94%E8%B3%BD%E7%85%A7%E7%89%87\" aria-label=\"比賽照片 permalink\" class=\"anchor\"><svg aria-hidden=\"true\" focusable=\"false\" height=\"16\" version=\"1.1\" viewBox=\"0 0 16 16\" width=\"16\"><path fill-rule=\"evenodd\" d=\"M4 9h1v1H4c-1.5 0-3-1.69-3-3.5S2.55 3 4 3h4c1.45 0 3 1.69 3 3.5 0 1.41-.91 2.72-2 3.25V8.59c.58-.45 1-1.27 1-2.09C10 5.22 8.98 4 8 4H4c-.98 0-2 1.22-2 2.5S3 9 4 9zm9-3h-1v1h1c1 0 2 1.22 2 2.5S13.98 12 13 12H9c-.98 0-2-1.22-2-2.5 0-.83.42-1.64 1-2.09V6.25c-1.09.53-2 1.84-2 3.25C6 11.31 7.55 13 9 13h4c1.45 0 3-1.69 3-3.5S14.5 6 13 6z\"></path></svg></a>比賽照片</h2>\n<p>以下是比賽時拍攝的一些照片：</p>\n<p><img src=\"https://i.imgur.com/vXyDaoY.jpg\" alt=\"Imgur\"></p>\n<p>感謝這次一起參賽的三位隊友。</p>\n<p><img src=\"https://i.imgur.com/6nLsXEB.jpg\" alt=\"Imgur\"></p>\n<center>比賽場地</center>\n<p><img src=\"https://i.imgur.com/2mLCtBm.jpg\" alt=\"Imgur\"></p>\n<center>接待處</center>\n<p><img src=\"https://i.imgur.com/pL19qZw.jpg\" alt=\"Imgur\"></p>\n<center>宣傳物品</center>\n<p><img src=\"https://i.imgur.com/g1GZHCJ.jpg\" alt=\"Imgur\"></p>\n<center>平常用來賣官方廣告的地方現在用來賣hackUST和hardUST的廣告 XD</center>\n<p><img src=\"https://i.imgur.com/DbLEVGz.jpg\" alt=\"Imgur\"></p>\n<center>演示的場地</center>\n<p>這次主辦單位派發了港幣 120 元的餐券，還有很多零食，飲料。最重要的是，有我最喜歡的忌廉汽水 www。希望以後都可以繼續參加比賽，學習更多的編程知識。</p>\n<h2 id=\"參考資料\"><a href=\"#%E5%8F%83%E8%80%83%E8%B3%87%E6%96%99\" aria-label=\"參考資料 permalink\" class=\"anchor\"><svg aria-hidden=\"true\" focusable=\"false\" height=\"16\" version=\"1.1\" viewBox=\"0 0 16 16\" width=\"16\"><path fill-rule=\"evenodd\" d=\"M4 9h1v1H4c-1.5 0-3-1.69-3-3.5S2.55 3 4 3h4c1.45 0 3 1.69 3 3.5 0 1.41-.91 2.72-2 3.25V8.59c.58-.45 1-1.27 1-2.09C10 5.22 8.98 4 8 4H4c-.98 0-2 1.22-2 2.5S3 9 4 9zm9-3h-1v1h1c1 0 2 1.22 2 2.5S13.98 12 13 12H9c-.98 0-2-1.22-2-2.5 0-.83.42-1.64 1-2.09V6.25c-1.09.53-2 1.84-2 3.25C6 11.31 7.55 13 9 13h4c1.45 0 3-1.69 3-3.5S14.5 6 13 6z\"></path></svg></a>參考資料</h2>\n<ol>\n<li><a href=\"https://developer.mozilla.org/en-US/docs/Web/API/Detecting_device_orientation\" target=\"_blank\" rel=\"nofollow noopener noreferrer\">Detecting device orientation - MDN</a></li>\n<li><a href=\"https://socket.io/docs/\" target=\"_blank\" rel=\"nofollow noopener noreferrer\">Socket.io 官方文檔</a></li>\n<li><a href=\"http://c3js.org/gettingstarted.html\" target=\"_blank\" rel=\"nofollow noopener noreferrer\">C3.js 官方 Starter</a></li>\n</ol>","tableOfContents":"<ul>\n<li><a href=\"/2017/04/23/hackUST-2017-hackathon-summary/#%E6%8A%80%E8%A1%93%E7%B4%B0%E7%AF%80\">技術細節</a></li>\n<li><a href=\"/2017/04/23/hackUST-2017-hackathon-summary/#%E6%AF%94%E8%B3%BD%E7%85%A7%E7%89%87\">比賽照片</a></li>\n<li><a href=\"/2017/04/23/hackUST-2017-hackathon-summary/#%E5%8F%83%E8%80%83%E8%B3%87%E6%96%99\">參考資料</a></li>\n</ul>","excerpt":"經過一天的努力，我們成功進入最後 5 強。這次比賽都幾好玩，基本上由第一天中午吃到晚上，然後第二天回來也是吃吃吃。雖然最後沒有取得獎金，但也是學到很多的知識。比如說如何解決安裝 npm package 問題，更新 npm package 問題。第一天中午的時候已經把 Demo…","fields":{"slug":"/2017/04/23/hackUST-2017-hackathon-summary/"},"frontmatter":{"id":"20170423a","title":"hackUST 2017 後記","slug":"/2017/04/23/hackUST-2017-hackathon-summary/","date":"2017-04-23T03:48:03.125Z","headerImage":null}},"previous":null,"next":null}]}},"pageContext":{"isCreatedByStatefulCreatePages":false,"id":"6daa1693-f316-5382-9102-a13a93c9c63f","index":36}}